{"slug": "print_line_before", "openemoji": "1F423", "disp_title": "print line before match", "version": 5, "author": "mmr", "example": "awk '/404/{print a}{a=$0}' **/access.log*", "description": "Print all matching lines (without the filename or the file path) in all files under the current directory that start with \"access.log\", where the next line contains the string \"404\".\n\nNote that you will need to search recursively.\n", "completions": ["access.log"], "expected_output": {"order": false, "lines": ["251.111.109.143 - - [09/Jan/2017:22:49:02 +0100] \"GET /posts/foo?appID=xxxx HTTP/1.0\" 200 2477", "17.137.186.194 - - [09/Jan/2017:22:43:17 +0100] \"GET /pages/create HTTP/1.0\" 200 1116", "89.148.148.238 - - [09/Jan/2017:22:33:09 +0100] \"GET /posts/1/display HTTP/1.0\" 502 2477", "138.212.253.84 - - [09/Jan/2017:22:53:54 +0100] \"GET /posts/foo?appID=xxxx HTTP/1.0\" 200 3471"]}}